pixl/__init__.py
pixl/utils.py
pixl-0.2.dist-info/METADATA
pixl-0.2.dist-info/WHEEL
pixl-0.2.dist-info/top_level.txt
pixl-0.2.dist-info/RECORD
